findthegap/__init__.py
findthegap/gapper.py
findthegap/quarticKDE.py
findthegap-0.0.10.dist-info/LICENSE
findthegap-0.0.10.dist-info/METADATA
findthegap-0.0.10.dist-info/WHEEL
findthegap-0.0.10.dist-info/top_level.txt
findthegap-0.0.10.dist-info/RECORD
