Metadata-Version: 2.1
Name: findthegap
Version: 0.0.10
License-File: LICENSE
